__init__.py
manager.py
projecteer.py
replacer.py
cli_tools/__init__.py
cli_tools/colorprint.py
cli_tools/cursor.py
cmds/__init__.py
cmds/cleanup.py
cmds/stats.py
parse/__init__.py
parse/config_parser.py
parse/script_parser.py
projecteer-0.1.11.dist-info/METADATA
projecteer-0.1.11.dist-info/WHEEL
projecteer-0.1.11.dist-info/entry_points.txt
projecteer-0.1.11.dist-info/license
projecteer-0.1.11.dist-info/top_level.txt
projecteer-0.1.11.dist-info/RECORD
