Metadata-Version: 2.1
Name: projecteer
Version: 0.1.11
Summary: Helps you keep your project together
Project-URL: Homepage, https://github.com/TruFelix/projecteer
Project-URL: Bug Tracker, https://github.com/TruFelix/projecteer/issues
License-File: license
Requires-Dist: termcolor
